MANIFEST.in
README.md
README.rst
setup.py
django_gearman_jbox/__init__.py
django_gearman_jbox/decorators.py
django_gearman_jbox/models.py
django_gearman_jbox/settings.py
django_gearman_jbox.egg-info/PKG-INFO
django_gearman_jbox.egg-info/SOURCES.txt
django_gearman_jbox.egg-info/dependency_links.txt
django_gearman_jbox.egg-info/not-zip-safe
django_gearman_jbox.egg-info/requires.txt
django_gearman_jbox.egg-info/top_level.txt
django_gearman_jbox/management/__init__.py
django_gearman_jbox/management/commands/__init__.py
django_gearman_jbox/management/commands/gearman_client_example.py
django_gearman_jbox/management/commands/gearman_server_info.py
django_gearman_jbox/management/commands/gearman_worker.py