Metadata-Version: 1.1
Name: django-gearman-jbox
Version: 0.1
Summary: A convenience wrapper for Gearman clients and workers in Django/Python
Home-page: http://jbox-web.github.com/django-gearman-jbox/
Author: Nicolas Rodriguez
Author-email: nrodriguez@jbox-web.com
License: MPL
Download-URL: http://jbox-web.github.com/django-gearman-jbox/
Keywords: django,gearman,jobs,tasks,asynchronous
Platform: Linux
Classifier: Development Status :: 4 - Beta
Classifier: Environment :: Web Environment
Classifier: Framework :: Django
Classifier: Intended Audience :: Developers
Classifier: Intended Audience :: System Administrators
Classifier: Natural Language :: English
Classifier: Operating System :: OS Independent
Classifier: Programming Language :: Python
Classifier: Topic :: Software Development :: Libraries :: Python Modules
